{
  "name": "iina-plugin-thunder-subtitle",
  "identifier": "fun.magicdawn.iina-plugin-thunder-subtitle",
  "version": "0.0.1",
  "ghVersion": 3,
  "ghRepo": "magicdawn/iina-plugin-thunder-subtitle-dist",
  "description": "search subtitle from thunder",
  "author": {
    "name": "magicdawn",
    "email": "magicdawn@qq.com",
    "url": "https://iina.io"
  },
  "entry": "dist/index.js",
  "globalEntry": "dist/global.js",
  "permissions": ["show-osd", "network-request", "video-overlay", "file-system"],
  "allowedDomains": ["*.xunlei.com", "*.geilijiasu.com"],
  "preferencesPage": "",
  "preferenceDefaults": {}
}
